{
  "accuracy": null,
  "contest_combos": null,
  "contest_effect": {
    "url": "/contest-effect/20/"
  },
  "contest_type": {
    "name": "cute",
    "url": "/contest-type/3/"
  },
  "damage_class": {
    "name": "status",
    "url": "/move-damage-class/1/"
  },
  "effect_chance": null,
  "effect_changes": [],
  "effect_entries": [
    {
      "effect": "User's ability is replaced with the target's until the user leaves the field.  Ignores accuracy and evasion modifiers.\n\nIf the target has flower gift, forecast, illusion, imposter, multitype, stance change, trace, wonder guard, or zen mode, this move will fail.\n\nThis move cannot be copied by mirror move.",
      "language": {
        "name": "en",
        "url": "/language/9/"
      },
      "short_effect": "Copies the target's ability."
    }
  ],
  "flavor_text_entries": [
    {
      "flavor_text": "Imita al objetivo por completo y copia su habilidad. ",
      "language": {
        "name": "es",
        "url": "/language/7/"
      },
      "version_group": {
        "name": "ultra-sun-ultra-moon",
        "url": "/version-group/18/"
      }
    },
    {
      "flavor_text": "Mimics the target and\ncopies its special ability.",
      "language": {
        "name": "en",
        "url": "/language/9/"
      },
      "version_group": {
        "name": "ruby-sapphire",
        "url": "/version-group/5/"
      }
    },
    {
      "flavor_text": "Mimics the target and\ncopies its special ability.",
      "language": {
        "name": "en",
        "url": "/language/9/"
      },
      "version_group": {
        "name": "emerald",
        "url": "/version-group/6/"
      }
    },
    {
      "flavor_text": "The user mimics the\nfoe completely and\ncopies the foe’s\nability.",
      "language": {
        "name": "en",
        "url": "/language/9/"
      },
      "version_group": {
        "name": "firered-leafgreen",
        "url": "/version-group/7/"
      }
    },
    {
      "flavor_text": "The user mimics the\nfoe completely,\ncopying the foe’s\nnatural ability.\n",
      "language": {
        "name": "en",
        "url": "/language/9/"
      },
      "version_group": {
        "name": "diamond-pearl",
        "url": "/version-group/8/"
      }
    },
    {
      "flavor_text": "The user mimics the\nfoe completely,\ncopying the foe’s\nnatural ability.\n",
      "language": {
        "name": "en",
        "url": "/language/9/"
      },
      "version_group": {
        "name": "platinum",
        "url": "/version-group/9/"
      }
    },
    {
      "flavor_text": "The user mimics the\nfoe completely,\ncopying the foe’s\nnatural ability.\n",
      "language": {
        "name": "en",
        "url": "/language/9/"
      },
      "version_group": {
        "name": "heartgold-soulsilver",
        "url": "/version-group/10/"
      }
    },
    {
      "flavor_text": "Imite la cible et copie\nsa capacité spéciale.",
      "language": {
        "name": "fr",
        "url": "/language/5/"
      },
      "version_group": {
        "name": "black-white",
        "url": "/version-group/11/"
      }
    },
    {
      "flavor_text": "The user mimics the target completely,\ncopying the target’s natural Ability.",
      "language": {
        "name": "en",
        "url": "/language/9/"
      },
      "version_group": {
        "name": "black-white",
        "url": "/version-group/11/"
      }
    },
    {
      "flavor_text": "The user mimics the target completely,\ncopying the target’s natural Ability.",
      "language": {
        "name": "en",
        "url": "/language/9/"
      },
      "version_group": {
        "name": "black-2-white-2",
        "url": "/version-group/14/"
      }
    },
    {
      "flavor_text": "あいてに　なりきって　じぶんも　あいてと\nおなじ　とくせいに　へんかする。\n",
      "language": {
        "name": "ja-Hrkt",
        "url": "/language/1/"
      },
      "version_group": {
        "name": "x-y",
        "url": "/version-group/15/"
      }
    },
    {
      "flavor_text": "상대의 역할을 하여 자신도 상대와\n같은 특성으로 변화한다.",
      "language": {
        "name": "ko",
        "url": "/language/3/"
      },
      "version_group": {
        "name": "x-y",
        "url": "/version-group/15/"
      }
    },
    {
      "flavor_text": "Imite la cible et copie son talent.",
      "language": {
        "name": "fr",
        "url": "/language/5/"
      },
      "version_group": {
        "name": "x-y",
        "url": "/version-group/15/"
      }
    },
    {
      "flavor_text": "Parodiert das Ziel und kopiert seine Fähigkeit.",
      "language": {
        "name": "de",
        "url": "/language/6/"
      },
      "version_group": {
        "name": "x-y",
        "url": "/version-group/15/"
      }
    },
    {
      "flavor_text": "Imita al objetivo por completo y copia su habilidad.",
      "language": {
        "name": "es",
        "url": "/language/7/"
      },
      "version_group": {
        "name": "x-y",
        "url": "/version-group/15/"
      }
    },
    {
      "flavor_text": "Chi la usa mima in tutto il bersaglio, copiandone\nl’abilità.",
      "language": {
        "name": "it",
        "url": "/language/8/"
      },
      "version_group": {
        "name": "x-y",
        "url": "/version-group/15/"
      }
    },
    {
      "flavor_text": "The user mimics the target completely,\ncopying the target’s natural Ability.",
      "language": {
        "name": "en",
        "url": "/language/9/"
      },
      "version_group": {
        "name": "x-y",
        "url": "/version-group/15/"
      }
    },
    {
      "flavor_text": "相手に　なりきって　自分も　相手と\n同じ　特性に　変化する。\n",
      "language": {
        "name": "ja",
        "url": "/language/11/"
      },
      "version_group": {
        "name": "x-y",
        "url": "/version-group/15/"
      }
    },
    {
      "flavor_text": "あいてに　なりきって　じぶんも　あいてと\nおなじ　とくせいに　へんかする。\n",
      "language": {
        "name": "ja-Hrkt",
        "url": "/language/1/"
      },
      "version_group": {
        "name": "omega-ruby-alpha-sapphire",
        "url": "/version-group/16/"
      }
    },
    {
      "flavor_text": "상대의 역할을 하여 자신도 상대와\n같은 특성으로 변화한다.",
      "language": {
        "name": "ko",
        "url": "/language/3/"
      },
      "version_group": {
        "name": "omega-ruby-alpha-sapphire",
        "url": "/version-group/16/"
      }
    },
    {
      "flavor_text": "Imite la cible et copie son talent.",
      "language": {
        "name": "fr",
        "url": "/language/5/"
      },
      "version_group": {
        "name": "omega-ruby-alpha-sapphire",
        "url": "/version-group/16/"
      }
    },
    {
      "flavor_text": "Parodiert das Ziel und kopiert seine Fähigkeit.",
      "language": {
        "name": "de",
        "url": "/language/6/"
      },
      "version_group": {
        "name": "omega-ruby-alpha-sapphire",
        "url": "/version-group/16/"
      }
    },
    {
      "flavor_text": "Imita al objetivo por completo y copia su habilidad. ",
      "language": {
        "name": "es",
        "url": "/language/7/"
      },
      "version_group": {
        "name": "omega-ruby-alpha-sapphire",
        "url": "/version-group/16/"
      }
    },
    {
      "flavor_text": "Chi la usa mima in tutto il bersaglio, copiandone\nl’abilità.",
      "language": {
        "name": "it",
        "url": "/language/8/"
      },
      "version_group": {
        "name": "omega-ruby-alpha-sapphire",
        "url": "/version-group/16/"
      }
    },
    {
      "flavor_text": "The user mimics the target completely,\ncopying the target’s natural Ability.",
      "language": {
        "name": "en",
        "url": "/language/9/"
      },
      "version_group": {
        "name": "omega-ruby-alpha-sapphire",
        "url": "/version-group/16/"
      }
    },
    {
      "flavor_text": "相手に　なりきって　自分も　相手と\n同じ　特性に　変化する。\n",
      "language": {
        "name": "ja",
        "url": "/language/11/"
      },
      "version_group": {
        "name": "omega-ruby-alpha-sapphire",
        "url": "/version-group/16/"
      }
    },
    {
      "flavor_text": "あいてに　なりきって　じぶんも　あいてと\nおなじ　とくせいに　へんかする。",
      "language": {
        "name": "ja-Hrkt",
        "url": "/language/1/"
      },
      "version_group": {
        "name": "sun-moon",
        "url": "/version-group/17/"
      }
    },
    {
      "flavor_text": "상대의 역할을 하여 자신도 상대와\n같은 특성으로 변화한다.",
      "language": {
        "name": "ko",
        "url": "/language/3/"
      },
      "version_group": {
        "name": "sun-moon",
        "url": "/version-group/17/"
      }
    },
    {
      "flavor_text": "扮演成對手，\n讓自己的特性\n也變得和對手相同。",
      "language": {
        "name": "zh-Hant",
        "url": "/language/4/"
      },
      "version_group": {
        "name": "sun-moon",
        "url": "/version-group/17/"
      }
    },
    {
      "flavor_text": "Imite la cible et copie son talent.",
      "language": {
        "name": "fr",
        "url": "/language/5/"
      },
      "version_group": {
        "name": "sun-moon",
        "url": "/version-group/17/"
      }
    },
    {
      "flavor_text": "Ahmt das Ziel nach und kopiert seine Fähigkeit.",
      "language": {
        "name": "de",
        "url": "/language/6/"
      },
      "version_group": {
        "name": "sun-moon",
        "url": "/version-group/17/"
      }
    },
    {
      "flavor_text": "Imita al objetivo por completo y copia su habilidad. ",
      "language": {
        "name": "es",
        "url": "/language/7/"
      },
      "version_group": {
        "name": "sun-moon",
        "url": "/version-group/17/"
      }
    },
    {
      "flavor_text": "Chi la usa mima in tutto il bersaglio, copiandone\nl’abilità.",
      "language": {
        "name": "it",
        "url": "/language/8/"
      },
      "version_group": {
        "name": "sun-moon",
        "url": "/version-group/17/"
      }
    },
    {
      "flavor_text": "The user mimics the target completely, copying the\ntarget’s natural Ability.",
      "language": {
        "name": "en",
        "url": "/language/9/"
      },
      "version_group": {
        "name": "sun-moon",
        "url": "/version-group/17/"
      }
    },
    {
      "flavor_text": "相手に　なりきって　自分も　相手と\n同じ　特性に　変化する。",
      "language": {
        "name": "ja",
        "url": "/language/11/"
      },
      "version_group": {
        "name": "sun-moon",
        "url": "/version-group/17/"
      }
    },
    {
      "flavor_text": "扮演对手，\n让自己的特性\n变得和对手相同。",
      "language": {
        "name": "zh-Hans",
        "url": "/language/12/"
      },
      "version_group": {
        "name": "sun-moon",
        "url": "/version-group/17/"
      }
    },
    {
      "flavor_text": "あいてに　なりきって　じぶんも　あいてと\nおなじ　とくせいに　へんかする。",
      "language": {
        "name": "ja-Hrkt",
        "url": "/language/1/"
      },
      "version_group": {
        "name": "ultra-sun-ultra-moon",
        "url": "/version-group/18/"
      }
    },
    {
      "flavor_text": "상대의 역할을 하여 자신도 상대와\n같은 특성으로 변화한다.",
      "language": {
        "name": "ko",
        "url": "/language/3/"
      },
      "version_group": {
        "name": "ultra-sun-ultra-moon",
        "url": "/version-group/18/"
      }
    },
    {
      "flavor_text": "扮演成對手，\n讓自己的特性\n也變得和對手相同。",
      "language": {
        "name": "zh-Hant",
        "url": "/language/4/"
      },
      "version_group": {
        "name": "ultra-sun-ultra-moon",
        "url": "/version-group/18/"
      }
    },
    {
      "flavor_text": "Imite la cible et copie son talent.",
      "language": {
        "name": "fr",
        "url": "/language/5/"
      },
      "version_group": {
        "name": "ultra-sun-ultra-moon",
        "url": "/version-group/18/"
      }
    },
    {
      "flavor_text": "Ahmt das Ziel nach und kopiert seine Fähigkeit.",
      "language": {
        "name": "de",
        "url": "/language/6/"
      },
      "version_group": {
        "name": "ultra-sun-ultra-moon",
        "url": "/version-group/18/"
      }
    },
    {
      "flavor_text": "Chi la usa mima in tutto il bersaglio, copiandone\nl’abilità.",
      "language": {
        "name": "it",
        "url": "/language/8/"
      },
      "version_group": {
        "name": "ultra-sun-ultra-moon",
        "url": "/version-group/18/"
      }
    },
    {
      "flavor_text": "The user mimics the target completely, copying the\ntarget’s natural Ability.",
      "language": {
        "name": "en",
        "url": "/language/9/"
      },
      "version_group": {
        "name": "ultra-sun-ultra-moon",
        "url": "/version-group/18/"
      }
    },
    {
      "flavor_text": "相手に　なりきって　自分も　相手と\n同じ　特性に　変化する。",
      "language": {
        "name": "ja",
        "url": "/language/11/"
      },
      "version_group": {
        "name": "ultra-sun-ultra-moon",
        "url": "/version-group/18/"
      }
    },
    {
      "flavor_text": "扮演对手，\n让自己的特性\n变得和对手相同。",
      "language": {
        "name": "zh-Hans",
        "url": "/language/12/"
      },
      "version_group": {
        "name": "ultra-sun-ultra-moon",
        "url": "/version-group/18/"
      }
    },
    {
      "flavor_text": "あいてに　なりきって　じぶんも　あいてと\nおなじ　とくせいに　へんかする。",
      "language": {
        "name": "ja-Hrkt",
        "url": "/language/1/"
      },
      "version_group": {
        "name": "lets-go-pikachu-lets-go-eevee",
        "url": "/version-group/19/"
      }
    },
    {
      "flavor_text": "상대의 역할을 하여 자신도 상대와\n같은 특성으로 변화한다.",
      "language": {
        "name": "ko",
        "url": "/language/3/"
      },
      "version_group": {
        "name": "lets-go-pikachu-lets-go-eevee",
        "url": "/version-group/19/"
      }
    },
    {
      "flavor_text": "扮演成對手，\n讓自己的特性\n也變得和對手相同。",
      "language": {
        "name": "zh-Hant",
        "url": "/language/4/"
      },
      "version_group": {
        "name": "lets-go-pikachu-lets-go-eevee",
        "url": "/version-group/19/"
      }
    },
    {
      "flavor_text": "Imite la cible et copie son talent.",
      "language": {
        "name": "fr",
        "url": "/language/5/"
      },
      "version_group": {
        "name": "lets-go-pikachu-lets-go-eevee",
        "url": "/version-group/19/"
      }
    },
    {
      "flavor_text": "Ahmt das Ziel nach und kopiert seine Fähigkeit.",
      "language": {
        "name": "de",
        "url": "/language/6/"
      },
      "version_group": {
        "name": "lets-go-pikachu-lets-go-eevee",
        "url": "/version-group/19/"
      }
    },
    {
      "flavor_text": "Imita al objetivo por completo y copia su habilidad. ",
      "language": {
        "name": "es",
        "url": "/language/7/"
      },
      "version_group": {
        "name": "lets-go-pikachu-lets-go-eevee",
        "url": "/version-group/19/"
      }
    },
    {
      "flavor_text": "Chi la usa mima in tutto il bersaglio, copiandone\nl’abilità.",
      "language": {
        "name": "it",
        "url": "/language/8/"
      },
      "version_group": {
        "name": "lets-go-pikachu-lets-go-eevee",
        "url": "/version-group/19/"
      }
    },
    {
      "flavor_text": "The user mimics the target completely, copying the\ntarget’s natural Ability.",
      "language": {
        "name": "en",
        "url": "/language/9/"
      },
      "version_group": {
        "name": "lets-go-pikachu-lets-go-eevee",
        "url": "/version-group/19/"
      }
    },
    {
      "flavor_text": "相手に　なりきって　自分も　相手と\n同じ　特性に　変化する。",
      "language": {
        "name": "ja",
        "url": "/language/11/"
      },
      "version_group": {
        "name": "lets-go-pikachu-lets-go-eevee",
        "url": "/version-group/19/"
      }
    },
    {
      "flavor_text": "扮演对手，\n让自己的特性\n变得和对手相同。",
      "language": {
        "name": "zh-Hans",
        "url": "/language/12/"
      },
      "version_group": {
        "name": "lets-go-pikachu-lets-go-eevee",
        "url": "/version-group/19/"
      }
    },
    {
      "flavor_text": "あいてに　なりきって　じぶんも　あいてと\nおなじ　とくせいに　へんかする。",
      "language": {
        "name": "ja-Hrkt",
        "url": "/language/1/"
      },
      "version_group": {
        "name": "sword-shield",
        "url": "/version-group/20/"
      }
    },
    {
      "flavor_text": "상대의 역할을 하여 자신도 상대와\n같은 특성으로 변화한다.",
      "language": {
        "name": "ko",
        "url": "/language/3/"
      },
      "version_group": {
        "name": "sword-shield",
        "url": "/version-group/20/"
      }
    },
    {
      "flavor_text": "扮演成對手，\n讓自己的特性\n也變得和對手相同。",
      "language": {
        "name": "zh-Hant",
        "url": "/language/4/"
      },
      "version_group": {
        "name": "sword-shield",
        "url": "/version-group/20/"
      }
    },
    {
      "flavor_text": "Imite la cible et copie son talent.",
      "language": {
        "name": "fr",
        "url": "/language/5/"
      },
      "version_group": {
        "name": "sword-shield",
        "url": "/version-group/20/"
      }
    },
    {
      "flavor_text": "Ahmt das Ziel nach und kopiert seine Fähigkeit.",
      "language": {
        "name": "de",
        "url": "/language/6/"
      },
      "version_group": {
        "name": "sword-shield",
        "url": "/version-group/20/"
      }
    },
    {
      "flavor_text": "Imita al objetivo por completo y copia su habilidad. ",
      "language": {
        "name": "es",
        "url": "/language/7/"
      },
      "version_group": {
        "name": "sword-shield",
        "url": "/version-group/20/"
      }
    },
    {
      "flavor_text": "Chi la usa mima in tutto il bersaglio, copiandone\nl’abilità.",
      "language": {
        "name": "it",
        "url": "/language/8/"
      },
      "version_group": {
        "name": "sword-shield",
        "url": "/version-group/20/"
      }
    },
    {
      "flavor_text": "The user mimics the target completely, copying the\ntarget’s Ability.",
      "language": {
        "name": "en",
        "url": "/language/9/"
      },
      "version_group": {
        "name": "sword-shield",
        "url": "/version-group/20/"
      }
    },
    {
      "flavor_text": "相手に　なりきって　自分も　相手と\n同じ　特性に　変化する。",
      "language": {
        "name": "ja",
        "url": "/language/11/"
      },
      "version_group": {
        "name": "sword-shield",
        "url": "/version-group/20/"
      }
    },
    {
      "flavor_text": "扮演对手，\n让自己的特性\n变得和对手相同。",
      "language": {
        "name": "zh-Hans",
        "url": "/language/12/"
      },
      "version_group": {
        "name": "sword-shield",
        "url": "/version-group/20/"
      }
    }
  ],
  "generation": {
    "name": "generation-iii",
    "url": "/generation/3/"
  },
  "id": 272,
  "learned_by_pokemon": [
    {
      "name": "clefairy",
      "url": "/pokemon/35/"
    },
    {
      "name": "clefable",
      "url": "/pokemon/36/"
    },
    {
      "name": "vulpix",
      "url": "/pokemon/37/"
    },
    {
      "name": "ninetales",
      "url": "/pokemon/38/"
    },
    {
      "name": "jigglypuff",
      "url": "/pokemon/39/"
    },
    {
      "name": "wigglytuff",
      "url": "/pokemon/40/"
    },
    {
      "name": "psyduck",
      "url": "/pokemon/54/"
    },
    {
      "name": "golduck",
      "url": "/pokemon/55/"
    },
    {
      "name": "mankey",
      "url": "/pokemon/56/"
    },
    {
      "name": "primeape",
      "url": "/pokemon/57/"
    },
    {
      "name": "abra",
      "url": "/pokemon/63/"
    },
    {
      "name": "kadabra",
      "url": "/pokemon/64/"
    },
    {
      "name": "alakazam",
      "url": "/pokemon/65/"
    },
    {
      "name": "machop",
      "url": "/pokemon/66/"
    },
    {
      "name": "machoke",
      "url": "/pokemon/67/"
    },
    {
      "name": "machamp",
      "url": "/pokemon/68/"
    },
    {
      "name": "gengar",
      "url": "/pokemon/94/"
    },
    {
      "name": "drowzee",
      "url": "/pokemon/96/"
    },
    {
      "name": "hypno",
      "url": "/pokemon/97/"
    },
    {
      "name": "hitmonlee",
      "url": "/pokemon/106/"
    },
    {
      "name": "hitmonchan",
      "url": "/pokemon/107/"
    },
    {
      "name": "mr-mime",
      "url": "/pokemon/122/"
    },
    {
      "name": "jynx",
      "url": "/pokemon/124/"
    },
    {
      "name": "tauros",
      "url": "/pokemon/128/"
    },
    {
      "name": "mewtwo",
      "url": "/pokemon/150/"
    },
    {
      "name": "mew",
      "url": "/pokemon/151/"
    },
    {
      "name": "cleffa",
      "url": "/pokemon/173/"
    },
    {
      "name": "igglybuff",
      "url": "/pokemon/174/"
    },
    {
      "name": "sudowoodo",
      "url": "/pokemon/185/"
    },
    {
      "name": "aipom",
      "url": "/pokemon/190/"
    },
    {
      "name": "houndour",
      "url": "/pokemon/228/"
    },
    {
      "name": "houndoom",
      "url": "/pokemon/229/"
    },
    {
      "name": "stantler",
      "url": "/pokemon/234/"
    },
    {
      "name": "tyrogue",
      "url": "/pokemon/236/"
    },
    {
      "name": "hitmontop",
      "url": "/pokemon/237/"
    },
    {
      "name": "smoochum",
      "url": "/pokemon/238/"
    },
    {
      "name": "blaziken",
      "url": "/pokemon/257/"
    },
    {
      "name": "makuhita",
      "url": "/pokemon/296/"
    },
    {
      "name": "hariyama",
      "url": "/pokemon/297/"
    },
    {
      "name": "sableye",
      "url": "/pokemon/302/"
    },
    {
      "name": "meditite",
      "url": "/pokemon/307/"
    },
    {
      "name": "medicham",
      "url": "/pokemon/308/"
    },
    {
      "name": "spoink",
      "url": "/pokemon/325/"
    },
    {
      "name": "grumpig",
      "url": "/pokemon/326/"
    },
    {
      "name": "spinda",
      "url": "/pokemon/327/"
    },
    {
      "name": "cacnea",
      "url": "/pokemon/331/"
    },
    {
      "name": "cacturne",
      "url": "/pokemon/332/"
    },
    {
      "name": "kecleon",
      "url": "/pokemon/352/"
    },
    {
      "name": "shuppet",
      "url": "/pokemon/353/"
    },
    {
      "name": "banette",
      "url": "/pokemon/354/"
    },
    {
      "name": "absol",
      "url": "/pokemon/359/"
    },
    {
      "name": "latias",
      "url": "/pokemon/380/"
    },
    {
      "name": "deoxys-normal",
      "url": "/pokemon/386/"
    },
    {
      "name": "chimchar",
      "url": "/pokemon/390/"
    },
    {
      "name": "monferno",
      "url": "/pokemon/391/"
    },
    {
      "name": "infernape",
      "url": "/pokemon/392/"
    },
    {
      "name": "ambipom",
      "url": "/pokemon/424/"
    },
    {
      "name": "bonsly",
      "url": "/pokemon/438/"
    },
    {
      "name": "mime-jr",
      "url": "/pokemon/439/"
    },
    {
      "name": "chatot",
      "url": "/pokemon/441/"
    },
    {
      "name": "riolu",
      "url": "/pokemon/447/"
    },
    {
      "name": "lucario",
      "url": "/pokemon/448/"
    },
    {
      "name": "croagunk",
      "url": "/pokemon/453/"
    },
    {
      "name": "toxicroak",
      "url": "/pokemon/454/"
    },
    {
      "name": "snover",
      "url": "/pokemon/459/"
    },
    {
      "name": "abomasnow",
      "url": "/pokemon/460/"
    },
    {
      "name": "uxie",
      "url": "/pokemon/480/"
    },
    {
      "name": "mesprit",
      "url": "/pokemon/481/"
    },
    {
      "name": "azelf",
      "url": "/pokemon/482/"
    },
    {
      "name": "victini",
      "url": "/pokemon/494/"
    },
    {
      "name": "purrloin",
      "url": "/pokemon/509/"
    },
    {
      "name": "liepard",
      "url": "/pokemon/510/"
    },
    {
      "name": "pansage",
      "url": "/pokemon/511/"
    },
    {
      "name": "simisage",
      "url": "/pokemon/512/"
    },
    {
      "name": "pansear",
      "url": "/pokemon/513/"
    },
    {
      "name": "simisear",
      "url": "/pokemon/514/"
    },
    {
      "name": "panpour",
      "url": "/pokemon/515/"
    },
    {
      "name": "simipour",
      "url": "/pokemon/516/"
    },
    {
      "name": "audino",
      "url": "/pokemon/531/"
    },
    {
      "name": "lilligant",
      "url": "/pokemon/549/"
    },
    {
      "name": "yamask",
      "url": "/pokemon/562/"
    },
    {
      "name": "cofagrigus",
      "url": "/pokemon/563/"
    },
    {
      "name": "gothita",
      "url": "/pokemon/574/"
    },
    {
      "name": "gothorita",
      "url": "/pokemon/575/"
    },
    {
      "name": "gothitelle",
      "url": "/pokemon/576/"
    },
    {
      "name": "solosis",
      "url": "/pokemon/577/"
    },
    {
      "name": "duosion",
      "url": "/pokemon/578/"
    },
    {
      "name": "reuniclus",
      "url": "/pokemon/579/"
    },
    {
      "name": "elgyem",
      "url": "/pokemon/605/"
    },
    {
      "name": "beheeyem",
      "url": "/pokemon/606/"
    },
    {
      "name": "mienfoo",
      "url": "/pokemon/619/"
    },
    {
      "name": "mienshao",
      "url": "/pokemon/620/"
    },
    {
      "name": "pawniard",
      "url": "/pokemon/624/"
    },
    {
      "name": "bisharp",
      "url": "/pokemon/625/"
    },
    {
      "name": "tornadus-incarnate",
      "url": "/pokemon/641/"
    },
    {
      "name": "thundurus-incarnate",
      "url": "/pokemon/642/"
    },
    {
      "name": "landorus-incarnate",
      "url": "/pokemon/645/"
    },
    {
      "name": "meloetta-aria",
      "url": "/pokemon/648/"
    },
    {
      "name": "delphox",
      "url": "/pokemon/655/"
    },
    {
      "name": "froakie",
      "url": "/pokemon/656/"
    },
    {
      "name": "frogadier",
      "url": "/pokemon/657/"
    },
    {
      "name": "greninja",
      "url": "/pokemon/658/"
    },
    {
      "name": "furfrou",
      "url": "/pokemon/676/"
    },
    {
      "name": "espurr",
      "url": "/pokemon/677/"
    },
    {
      "name": "meowstic-male",
      "url": "/pokemon/678/"
    },
    {
      "name": "inkay",
      "url": "/pokemon/686/"
    },
    {
      "name": "malamar",
      "url": "/pokemon/687/"
    },
    {
      "name": "phantump",
      "url": "/pokemon/708/"
    },
    {
      "name": "trevenant",
      "url": "/pokemon/709/"
    },
    {
      "name": "pumpkaboo-average",
      "url": "/pokemon/710/"
    },
    {
      "name": "gourgeist-average",
      "url": "/pokemon/711/"
    },
    {
      "name": "hoopa",
      "url": "/pokemon/720/"
    },
    {
      "name": "oricorio-baile",
      "url": "/pokemon/741/"
    },
    {
      "name": "stufful",
      "url": "/pokemon/759/"
    },
    {
      "name": "bewear",
      "url": "/pokemon/760/"
    },
    {
      "name": "comfey",
      "url": "/pokemon/764/"
    },
    {
      "name": "sandygast",
      "url": "/pokemon/769/"
    },
    {
      "name": "palossand",
      "url": "/pokemon/770/"
    },
    {
      "name": "togedemaru",
      "url": "/pokemon/777/"
    },
    {
      "name": "dhelmise",
      "url": "/pokemon/781/"
    },
    {
      "name": "nihilego",
      "url": "/pokemon/793/"
    },
    {
      "name": "marshadow",
      "url": "/pokemon/802/"
    },
    {
      "name": "stakataka",
      "url": "/pokemon/805/"
    },
    {
      "name": "mr-rime",
      "url": "/pokemon/866/"
    },
    {
      "name": "wyrdeer",
      "url": "/pokemon/899/"
    },
    {
      "name": "deoxys-attack",
      "url": "/pokemon/10001/"
    },
    {
      "name": "deoxys-defense",
      "url": "/pokemon/10002/"
    },
    {
      "name": "deoxys-speed",
      "url": "/pokemon/10003/"
    },
    {
      "name": "meloetta-pirouette",
      "url": "/pokemon/10018/"
    },
    {
      "name": "tornadus-therian",
      "url": "/pokemon/10019/"
    },
    {
      "name": "thundurus-therian",
      "url": "/pokemon/10020/"
    },
    {
      "name": "landorus-therian",
      "url": "/pokemon/10021/"
    },
    {
      "name": "meowstic-female",
      "url": "/pokemon/10025/"
    },
    {
      "name": "pumpkaboo-small",
      "url": "/pokemon/10027/"
    },
    {
      "name": "pumpkaboo-large",
      "url": "/pokemon/10028/"
    },
    {
      "name": "pumpkaboo-super",
      "url": "/pokemon/10029/"
    },
    {
      "name": "gourgeist-small",
      "url": "/pokemon/10030/"
    },
    {
      "name": "gourgeist-large",
      "url": "/pokemon/10031/"
    },
    {
      "name": "gourgeist-super",
      "url": "/pokemon/10032/"
    },
    {
      "name": "alakazam-mega",
      "url": "/pokemon/10037/"
    },
    {
      "name": "gengar-mega",
      "url": "/pokemon/10038/"
    },
    {
      "name": "mewtwo-mega-x",
      "url": "/pokemon/10043/"
    },
    {
      "name": "mewtwo-mega-y",
      "url": "/pokemon/10044/"
    },
    {
      "name": "houndoom-mega",
      "url": "/pokemon/10048/"
    },
    {
      "name": "blaziken-mega",
      "url": "/pokemon/10050/"
    },
    {
      "name": "medicham-mega",
      "url": "/pokemon/10054/"
    },
    {
      "name": "banette-mega",
      "url": "/pokemon/10056/"
    },
    {
      "name": "absol-mega",
      "url": "/pokemon/10057/"
    },
    {
      "name": "lucario-mega",
      "url": "/pokemon/10059/"
    },
    {
      "name": "abomasnow-mega",
      "url": "/pokemon/10060/"
    },
    {
      "name": "latias-mega",
      "url": "/pokemon/10062/"
    },
    {
      "name": "sableye-mega",
      "url": "/pokemon/10066/"
    },
    {
      "name": "audino-mega",
      "url": "/pokemon/10069/"
    },
    {
      "name": "hoopa-unbound",
      "url": "/pokemon/10086/"
    },
    {
      "name": "vulpix-alola",
      "url": "/pokemon/10103/"
    },
    {
      "name": "ninetales-alola",
      "url": "/pokemon/10104/"
    },
    {
      "name": "greninja-battle-bond",
      "url": "/pokemon/10116/"
    },
    {
      "name": "greninja-ash",
      "url": "/pokemon/10117/"
    },
    {
      "name": "oricorio-pom-pom",
      "url": "/pokemon/10123/"
    },
    {
      "name": "oricorio-pau",
      "url": "/pokemon/10124/"
    },
    {
      "name": "oricorio-sensu",
      "url": "/pokemon/10125/"
    },
    {
      "name": "togedemaru-totem",
      "url": "/pokemon/10154/"
    },
    {
      "name": "mr-mime-galar",
      "url": "/pokemon/10168/"
    }
  ],
  "machines": [],
  "meta": {
    "ailment": {
      "name": "none",
      "url": "/move-ailment/0/"
    },
    "ailment_chance": 0,
    "category": {
      "name": "unique",
      "url": "/move-category/13/"
    },
    "crit_rate": 0,
    "drain": 0,
    "flinch_chance": 0,
    "healing": 0,
    "max_hits": null,
    "max_turns": null,
    "min_hits": null,
    "min_turns": null,
    "stat_chance": 0
  },
  "name": "role-play",
  "names": [
    {
      "language": {
        "name": "ja-Hrkt",
        "url": "/language/1/"
      },
      "name": "なりきり"
    },
    {
      "language": {
        "name": "ko",
        "url": "/language/3/"
      },
      "name": "역할"
    },
    {
      "language": {
        "name": "zh-Hant",
        "url": "/language/4/"
      },
      "name": "扮演"
    },
    {
      "language": {
        "name": "fr",
        "url": "/language/5/"
      },
      "name": "Imitation"
    },
    {
      "language": {
        "name": "de",
        "url": "/language/6/"
      },
      "name": "Rollenspiel"
    },
    {
      "language": {
        "name": "es",
        "url": "/language/7/"
      },
      "name": "Imitación"
    },
    {
      "language": {
        "name": "it",
        "url": "/language/8/"
      },
      "name": "Giocodiruolo"
    },
    {
      "language": {
        "name": "en",
        "url": "/language/9/"
      },
      "name": "Role Play"
    },
    {
      "language": {
        "name": "ja",
        "url": "/language/11/"
      },
      "name": "なりきり"
    },
    {
      "language": {
        "name": "zh-Hans",
        "url": "/language/12/"
      },
      "name": "扮演"
    }
  ],
  "past_values": [],
  "power": null,
  "pp": 10,
  "priority": 0,
  "stat_changes": [],
  "super_contest_effect": {
    "url": "/super-contest-effect/23/"
  },
  "target": {
    "name": "selected-pokemon",
    "url": "/move-target/10/"
  },
  "type": {
    "name": "psychic",
    "url": "/type/14/"
  }
}